odoo/addons/website_snippet_big_button/README.rst
odoo/addons/website_snippet_big_button/__init__.py
odoo/addons/website_snippet_big_button/__manifest__.py
odoo/addons/website_snippet_big_button/i18n/ca.po
odoo/addons/website_snippet_big_button/i18n/es.po
odoo/addons/website_snippet_big_button/i18n/fr.po
odoo/addons/website_snippet_big_button/i18n/hr.po
odoo/addons/website_snippet_big_button/i18n/it.po
odoo/addons/website_snippet_big_button/i18n/pt_BR.po
odoo/addons/website_snippet_big_button/i18n/sl.po
odoo/addons/website_snippet_big_button/i18n/website_snippet_big_button.pot
odoo/addons/website_snippet_big_button/readme/CONTRIBUTORS.md
odoo/addons/website_snippet_big_button/readme/DESCRIPTION.md
odoo/addons/website_snippet_big_button/readme/USAGE.md
odoo/addons/website_snippet_big_button/static/description/icon.png
odoo/addons/website_snippet_big_button/static/description/icon.svg
odoo/addons/website_snippet_big_button/static/description/index.html
odoo/addons/website_snippet_big_button/static/src/scss/website_snippet_big_button.scss
odoo/addons/website_snippet_big_button/templates/snippets.xml
odoo_addon_website_snippet_big_button-17.0.1.0.0.2.dist-info/METADATA
odoo_addon_website_snippet_big_button-17.0.1.0.0.2.dist-info/WHEEL
odoo_addon_website_snippet_big_button-17.0.1.0.0.2.dist-info/top_level.txt
odoo_addon_website_snippet_big_button-17.0.1.0.0.2.dist-info/RECORD
